labrinth/__init__.py
labrinth/labrinth.py
labrinth-0.1.2.dist-info/METADATA
labrinth-0.1.2.dist-info/WHEEL
labrinth-0.1.2.dist-info/top_level.txt
labrinth-0.1.2.dist-info/RECORD
