Metadata-Version: 2.1
Name: labrinth
Version: 0.1.2
Summary: A Python API wrapper for Modrinth (labrinth because why not)
Author: YourLocalMoon
Author-email: kovaslavs@gmail.com
Classifier: Programming Language :: Python :: 3
Classifier: License :: OSI Approved :: MIT License
Classifier: Operating System :: OS Independent
Requires-Python: >=3.6
Requires-Dist: requests
